monobank_handler/__init__.py
monobank_handler/client.py
monobank_handler/errors.py
monobank_handler/handler_utils/__init__.py
monobank_handler/handler_utils/freezone.py
monobank_handler/handler_utils/handler.py
monobank_handler/handler_utils/webhook_server.py
monobank_handler/signature.py
monobank_handler/transport.py
monobank_handler/utils.py
monobank_handler-0.1.7.dist-info/LICENSE
monobank_handler-0.1.7.dist-info/WHEEL
monobank_handler-0.1.7.dist-info/METADATA
monobank_handler-0.1.7.dist-info/RECORD
