Metadata-Version: 2.1
Name: monobank-handler
Version: 0.1.7
Summary: Monobank.ua API implementation with handlers(poll/webhook)
Home-page: https://github.com/bezumnui/monobank_handler
Author: George Viznyuk - (bezumnui)
Requires-Python: >=3.6,<4.0
Classifier: Programming Language :: Python :: 3
Classifier: Programming Language :: Python :: 3.10
Classifier: Programming Language :: Python :: 3.6
Classifier: Programming Language :: Python :: 3.7
Classifier: Programming Language :: Python :: 3.8
Classifier: Programming Language :: Python :: 3.9
Requires-Dist: ecdsa (>=0.13.2,<0.14.0)
Requires-Dist: requests (>=2.22,<3.0)
